scripts/__init__.py
scripts/cmd.py
tests/__init__.py
tests/test_collector.py
tests/test_parser.py
xltoy/__init__.py
xltoy/collector.py
xltoy/parser.py
xltoy/utils.py
xltoy-0.1.9.dist-info/LICENSE
xltoy-0.1.9.dist-info/METADATA
xltoy-0.1.9.dist-info/WHEEL
xltoy-0.1.9.dist-info/entry_points.txt
xltoy-0.1.9.dist-info/top_level.txt
xltoy-0.1.9.dist-info/RECORD
