Metadata-Version: 2.1
Name: xltoy
Version: 0.1.9
Summary: The ultimate toolkit for Microsoft Excel modelers and mod-operations.
Home-page: https://https://github.com/glaucouri/xltoy
Author: Glauco Uri
Author-email: glauco@uriland.it
License: UNKNOWN
Platform: UNKNOWN
Classifier: Programming Language :: Python :: 3
Classifier: Programming Language :: Python :: 3.6
Classifier: Programming Language :: Python :: 3.7
Classifier: Programming Language :: Python :: 3.8
Classifier: Programming Language :: Python :: 3.9
Classifier: License :: OSI Approved :: MIT License
Classifier: Operating System :: OS Independent
Classifier: Intended Audience :: Developers
Classifier: Intended Audience :: Financial and Insurance Industry
Classifier: Intended Audience :: System Administrators
Classifier: Intended Audience :: Information Technology
Requires-Python: >=3.6
Requires-Dist: openpyxl (>=3.0)
Requires-Dist: pyyaml (>=5.3)
Requires-Dist: dictdiffer
Requires-Dist: pyparsing (==2.4.7)
Requires-Dist: tox (>=3.20)
Requires-Dist: pytest
Requires-Dist: click
Requires-Dist: ujson (>=2.0.3)
Requires-Dist: networkx
